{"State.cce8949d-ea30-4d2f-bc17-bdd3883718da": {"id": "cce8949d-ea30-4d2f-bc17-bdd3883718da", "created_at": "2023-11-23T20:00:27.821506", "updated_at": "2023-11-23T20:00:27.821507", "name": "California", "__class__": "State"}, "State.1d611d3a-875e-49eb-97a4-8af12ae6ac37": {"id": "1d611d3a-875e-49eb-97a4-8af12ae6ac37", "created_at": "2023-11-23T20:00:27.821851", "updated_at": "2023-11-23T20:00:27.821852", "name": "Arizona", "__class__": "State"}, "Place.6c23b980-2d0b-4ce6-946d-2d06a97cc441": {"id": "6c23b980-2d0b-4ce6-946d-2d06a97cc441", "created_at": "2023-11-23T20:00:27.822377", "updated_at": "2023-11-23T20:00:27.822379", "city_id": "0001", "user_id": "0001", "name": "My little house", "number_rooms": 4, "number_bathrooms": 2, "max_guest": 10, "price_by_night": 300, "latitude": 37.773972, "longitude": -122.431297, "__class__": "Place"}, "State.2e7fa2ee-285c-42fa-99ac-63e8596aca00": {"id": "2e7fa2ee-285c-42fa-99ac-63e8596aca00", "created_at": "2023-11-23T13:41:29.525167", "updated_at": "2023-11-23T13:41:29.525188", "name": "California", "__class__": "State"}, "State.c178de28-e4c6-4241-870e-4a6ea3663143": {"id": "c178de28-e4c6-4241-870e-4a6ea3663143", "created_at": "2023-11-23T13:41:29.525470", "updated_at": "2023-11-23T13:41:29.525490", "name": "Arizona", "__class__": "State"}, "Place.b363a7fe-9b08-4dcb-8580-0ed72e74eb22": {"id": "b363a7fe-9b08-4dcb-8580-0ed72e74eb22", "created_at": "2023-11-23T13:41:29.526388", "updated_at": "2023-11-23T13:41:29.526403", "city_id": "0001", "user_id": "0001", "name": "My little house", "number_rooms": 4, "number_bathrooms": 2, "max_guest": 10, "price_by_night": 300, "latitude": 37.773972, "__class__": "Place"}, "State.52d8186c-0aa6-418b-9898-a76bb529572c": {"id": "52d8186c-0aa6-418b-9898-a76bb529572c", "created_at": "2023-11-23T14:18:12.422765", "updated_at": "2023-11-23T14:18:12.422768", "name": "California", "__class__": "State"}, "State.846291a6-d714-4a42-8f0e-9526ccacc162": {"id": "846291a6-d714-4a42-8f0e-9526ccacc162", "created_at": "2023-11-23T14:18:12.423342", "updated_at": "2023-11-23T14:18:12.423344", "name": "Nevada", "__class__": "State"}}